[
    {
        "ID": "0810054704434",
        "Name": "Jennifer Reed",
        "Lastname": "Osborn",
        "PhoneNumber": "160419531",
        "Country": "Saint Helena",
        "Text": "Toward focus hard worker. Throw process free ever. Week consumer catch tough.\nSuffer nice describe land thought most. Show between benefit pull personal.",
        "Date": "2022-01-21",
        "VisaCardNumber": "4055981589496675",
        "MastercardNumber": "5528592235796727",
        "AccountBalance": 247.21
    },
    {
        "ID": "5307225252809",
        "Name": "Jeremy Cohen",
        "Lastname": "Chambers",
        "PhoneNumber": "465010187",
        "Country": "Sri Lanka",
        "Text": "Eight research laugh. Responsibility cut maintain interview. Imagine attorney record tell actually economic.",
        "Date": "1985-05-17",
        "VisaCardNumber": "4504496386018298",
        "MastercardNumber": "5124105840664756",
        "AccountBalance": 6515.95
    },
    {
        "ID": "5304287199293",
        "Name": "Steven Wagner",
        "Lastname": "Holt",
        "PhoneNumber": "610806940",
        "Country": "Croatia",
        "Text": "Seem government time discuss fly put. Cell very senior record scene great. Police game camera although avoid whether size.",
        "Date": "1994-08-02",
        "VisaCardNumber": "4613801700652961",
        "MastercardNumber": "2680794598440346",
        "AccountBalance": 4136.28
    },
    {
        "ID": "1610047015098",
        "Name": "Luke Mejia",
        "Lastname": "Cherry",
        "PhoneNumber": "541685881",
        "Country": "Aruba",
        "Text": "Various picture modern many professional who. Arrive force structure exactly.\nDark he college buy only writer.\nMr bed bag receive bad. Day PM green upon. Lose lawyer past PM interesting civil.",
        "Date": "2006-02-11",
        "VisaCardNumber": "4161346961271081",
        "MastercardNumber": "5148598399266837",
        "AccountBalance": 9767.75
    },
    {
        "ID": "7607223992463",
        "Name": "Henry Bautista",
        "Lastname": "Stone",
        "PhoneNumber": "869893131",
        "Country": "Norway",
        "Text": "Ask method city detail herself dark. North decision base management. Financial only bank low while provide.",
        "Date": "1985-08-12",
        "VisaCardNumber": "4473812129207252",
        "MastercardNumber": "2241875788508745",
        "AccountBalance": 110.3
    },
    {
        "ID": "3905030800368",
        "Name": "Catherine Duncan",
        "Lastname": "Harris",
        "PhoneNumber": "709972632",
        "Country": "Bahrain",
        "Text": "Hear today bed especially range year ok. Project fight painting section.",
        "Date": "2022-01-08",
        "VisaCardNumber": "4199075581181844",
        "MastercardNumber": "2256526560702335",
        "AccountBalance": 9089.91
    },
    {
        "ID": "2503252396013",
        "Name": "Michael Cook",
        "Lastname": "Norman",
        "PhoneNumber": "965762578",
        "Country": "Zambia",
        "Text": "Party forget room however hope sign miss.\nCourt moment black even leader. Often structure name professional. Culture international though kind.\nRoad happen push lawyer strategy.",
        "Date": "1979-05-31",
        "VisaCardNumber": "4973829119896378",
        "MastercardNumber": "5398105076268057",
        "AccountBalance": 888.15
    },
    {
        "ID": "6807310895859",
        "Name": "David Johnson",
        "Lastname": "Wallace",
        "PhoneNumber": "849444423",
        "Country": "Solomon Islands",
        "Text": "Much because deal strong in sometimes yeah hold. Expert two even budget.\nOccur financial fall painting. Case box stand evening will policy.",
        "Date": "1982-05-05",
        "VisaCardNumber": "4095944660689412",
        "MastercardNumber": "2225624896610567",
        "AccountBalance": 1865.25
    },
    {
        "ID": "3003113260866",
        "Name": "Christina Winters",
        "Lastname": "Boyd",
        "PhoneNumber": "573816663",
        "Country": "Grenada",
        "Text": "Behavior up too political southern most. Size catch language hope support network build. Lot summer six pull Republican.",
        "Date": "2023-02-02",
        "VisaCardNumber": "4424461056868510",
        "MastercardNumber": "2241729250264552",
        "AccountBalance": 7260.95
    },
    {
        "ID": "4901176140388",
        "Name": "Ann Matthews",
        "Lastname": "Allen",
        "PhoneNumber": "143201679",
        "Country": "Nigeria",
        "Text": "Charge campaign officer carry capital between. Kind claim more part each good.\nOne green edge. Run approach realize as ready.",
        "Date": "2004-03-06",
        "VisaCardNumber": "4162850928092349",
        "MastercardNumber": "2242953076393127",
        "AccountBalance": 2055.3
    },
    {
        "ID": "4208206889799",
        "Name": "Alexandra Brown",
        "Lastname": "Jacobs",
        "PhoneNumber": "231362490",
        "Country": "Cape Verde",
        "Text": "On usually of east speech. Throughout without as. Democratic notice outside question lead.\nSection Mrs treat group low. Success treat practice since.",
        "Date": "2007-06-29",
        "VisaCardNumber": "4947491952263118",
        "MastercardNumber": "5131915523930170",
        "AccountBalance": 8124.94
    },
    {
        "ID": "1905302048893",
        "Name": "Thomas Torres",
        "Lastname": "Callahan",
        "PhoneNumber": "232370322",
        "Country": "Bolivia",
        "Text": "Growth wait phone bring very resource. Maintain door child subject. Issue plan reality five.\nTreat individual later market. Decade any power change moment teach race.",
        "Date": "2016-04-16",
        "VisaCardNumber": "4125070014746932",
        "MastercardNumber": "2223716015704990",
        "AccountBalance": 1876.74
    },
    {
        "ID": "1601288691803",
        "Name": "Mary Newton",
        "Lastname": "Sanders",
        "PhoneNumber": "558682870",
        "Country": "Georgia",
        "Text": "Spring against policy education authority dream. Official well very. Town short green spend. Wife either democratic pattern consider.\nWalk recognize economy off. Director adult hit movie better by.",
        "Date": "1977-05-07",
        "VisaCardNumber": "4360824973195117",
        "MastercardNumber": "2619486671606952",
        "AccountBalance": 4875.67
    },
    {
        "ID": "2110167148390",
        "Name": "Diane Harvey",
        "Lastname": "Jones",
        "PhoneNumber": "120694381",
        "Country": "Nicaragua",
        "Text": "Reflect art various shoulder kid rule brother gun. Time risk expect. Since certainly later huge listen exactly.",
        "Date": "1971-02-08",
        "VisaCardNumber": "4118721814325785",
        "MastercardNumber": "2391939568032371",
        "AccountBalance": 4922.94
    },
    {
        "ID": "4405016732072",
        "Name": "Mrs. Taylor Chambers",
        "Lastname": "Reyes",
        "PhoneNumber": "528297267",
        "Country": "Tonga",
        "Text": "Onto life old. Experience might once thing smile.\nPolitics sense wear police reason again can. Central today social wear.",
        "Date": "1993-07-23",
        "VisaCardNumber": "4145759796103116",
        "MastercardNumber": "5393733003202215",
        "AccountBalance": 1510.65
    },
    {
        "ID": "3210109750427",
        "Name": "Morgan Wilkinson",
        "Lastname": "Medina",
        "PhoneNumber": "956250867",
        "Country": "Myanmar",
        "Text": "Agent yard minute. Without so tend discussion. Side best whole relationship forget same. Goal military stuff myself eye economy.\nCoach administration movement true join fill view.",
        "Date": "2018-11-07",
        "VisaCardNumber": "4657426748242356",
        "MastercardNumber": "2277164588901138",
        "AccountBalance": 1167.9
    },
    {
        "ID": "0607261130957",
        "Name": "Timothy Miller",
        "Lastname": "Wells",
        "PhoneNumber": "851048965",
        "Country": "Singapore",
        "Text": "Suddenly main resource force medical. Production source be fall say TV bag.\nPractice film reality again. Program fine mind upon age light. Mouth behind author view entire form.",
        "Date": "1989-07-27",
        "VisaCardNumber": "4238336979181918",
        "MastercardNumber": "2521562223144408",
        "AccountBalance": 9349.96
    },
    {
        "ID": "6701019838435",
        "Name": "Sarah Rodriguez",
        "Lastname": "Smith",
        "PhoneNumber": "359041086",
        "Country": "Denmark",
        "Text": "After activity degree knowledge. Follow against should by both. Player partner method choose.\nPolitical full center hospital ground sometimes eat.",
        "Date": "1988-09-20",
        "VisaCardNumber": "4907447670569598",
        "MastercardNumber": "5134011482729998",
        "AccountBalance": 8533.8
    },
    {
        "ID": "7001137797247",
        "Name": "Matthew Massey",
        "Lastname": "Miller",
        "PhoneNumber": "569782568",
        "Country": "Bermuda",
        "Text": "That tax return explain. Size this sit grow good beat brother. Expert grow speak.\nDespite occur live late month. Head raise morning but check boy mind. Space send these because during sport answer.",
        "Date": "2001-04-09",
        "VisaCardNumber": "4268513537271992",
        "MastercardNumber": "5532806526564642",
        "AccountBalance": 5782.84
    },
    {
        "ID": "1308075224309",
        "Name": "Dr. Gabriel Navarro",
        "Lastname": "James",
        "PhoneNumber": "094418004",
        "Country": "Cuba",
        "Text": "Education cold modern she. Concern near truth show stop.",
        "Date": "2021-06-28",
        "VisaCardNumber": "4038840003454870",
        "MastercardNumber": "2547396064075599",
        "AccountBalance": 8362.16
    },
    {
        "ID": "4002126011838",
        "Name": "Wendy Manning",
        "Lastname": "Gonzalez",
        "PhoneNumber": "075995932",
        "Country": "Palestinian Territory",
        "Text": "Or and agent left any and develop improve.\nOffer total bit PM pass certainly gun. Rock house claim understand.",
        "Date": "1992-09-09",
        "VisaCardNumber": "4259310612094162",
        "MastercardNumber": "2285794220713952",
        "AccountBalance": 5139.44
    },
    {
        "ID": "8509040144983",
        "Name": "Jason Garcia",
        "Lastname": "Lutz",
        "PhoneNumber": "424199767",
        "Country": "Sri Lanka",
        "Text": "Score summer professional mission writer miss gas. Can her ground challenge beat.\nPhysical about development still finish she likely. Life realize watch car management.",
        "Date": "2012-02-27",
        "VisaCardNumber": "4458393944884541",
        "MastercardNumber": "5529979369625203",
        "AccountBalance": 8881.37
    },
    {
        "ID": "7506269953738",
        "Name": "Matthew Rogers",
        "Lastname": "Perez",
        "PhoneNumber": "159161114",
        "Country": "San Marino",
        "Text": "Professor ago best month could age. Mission quality study arrive fall after.\nHappen foot Democrat respond trip over year. Scientist talk read decide everybody possible. Surface individual price sea.",
        "Date": "2018-04-27",
        "VisaCardNumber": "4479646203802958",
        "MastercardNumber": "5597504938226452",
        "AccountBalance": 4840.73
    },
    {
        "ID": "0906144190770",
        "Name": "Lisa Rodriguez",
        "Lastname": "Bender",
        "PhoneNumber": "780145775",
        "Country": "Australia",
        "Text": "Environmental space four Congress base set eye. Dog summer idea culture measure ten whatever. Democrat store share military production.",
        "Date": "2005-09-13",
        "VisaCardNumber": "4402032571841997",
        "MastercardNumber": "2290115640158888",
        "AccountBalance": 6130.18
    },
    {
        "ID": "0504181336865",
        "Name": "Lori Klein",
        "Lastname": "Barker",
        "PhoneNumber": "833405928",
        "Country": "Guinea-Bissau",
        "Text": "Thing allow more place. Daughter firm reveal few. End fund work beyond reveal pay.\nTell tax decide culture music. Way yourself official through interview clear. Move once sure low recently soon.",
        "Date": "2014-11-24",
        "VisaCardNumber": "4489447931878495",
        "MastercardNumber": "2249876206086027",
        "AccountBalance": 8515.45
    },
    {
        "ID": "1807236168155",
        "Name": "Brittany Andrade",
        "Lastname": "Garcia",
        "PhoneNumber": "620248303",
        "Country": "Tokelau",
        "Text": "Station society fill magazine always foot. Friend property network.\nMention minute capital up second eye her. Man push fall another manage spring. Seven total whatever natural anyone deal already.",
        "Date": "1979-03-16",
        "VisaCardNumber": "4771201271398433",
        "MastercardNumber": "2702594294034912",
        "AccountBalance": 4977.71
    },
    {
        "ID": "0308127680938",
        "Name": "Robert Kim",
        "Lastname": "Brown",
        "PhoneNumber": "672193894",
        "Country": "Benin",
        "Text": "Particular both two meeting put management improve. Feeling pay girl event bring any.\nDaughter paper both red door vote seven blue. Teach her nature fill finish though.",
        "Date": "1980-12-31",
        "VisaCardNumber": "4899351855748904",
        "MastercardNumber": "5483010616125641",
        "AccountBalance": 1650.78
    },
    {
        "ID": "2612300399902",
        "Name": "Paul Brown",
        "Lastname": "Lopez",
        "PhoneNumber": "064470457",
        "Country": "Senegal",
        "Text": "Media into whether option analysis travel land appear. Plan old lead hour age evidence magazine. Then become must according vote news reduce.",
        "Date": "2008-03-23",
        "VisaCardNumber": "4182324668753490",
        "MastercardNumber": "2305757078189605",
        "AccountBalance": 9734.72
    },
    {
        "ID": "2101295716704",
        "Name": "Shawn Leblanc",
        "Lastname": "Hayes",
        "PhoneNumber": "091617376",
        "Country": "Norfolk Island",
        "Text": "Including heavy down result. Happy order begin give eat side service half.\nSeries today nature at. Forget card you play crime tax serious.",
        "Date": "1986-07-21",
        "VisaCardNumber": "4094495152492717",
        "MastercardNumber": "2720046149717850",
        "AccountBalance": 6083.56
    },
    {
        "ID": "5609033180058",
        "Name": "Steve Boyle",
        "Lastname": "Murray",
        "PhoneNumber": "928270140",
        "Country": "Bahrain",
        "Text": "Song I population car three. Service newspaper family. Glass best prepare agree listen third.\nRemember stay piece concern see boy difference. Lay total item significant.",
        "Date": "2016-02-02",
        "VisaCardNumber": "4772019346963935",
        "MastercardNumber": "5123136576609997",
        "AccountBalance": 9773.9
    },
    {
        "ID": "1911146644537",
        "Name": "William Moon",
        "Lastname": "Morgan",
        "PhoneNumber": "900961862",
        "Country": "Pakistan",
        "Text": "Camera lawyer his hope. Door hour experience finally strategy Republican result.\nDefense effort up movement. Nor choice a brother once school memory down. Quality again water to investment story.",
        "Date": "1991-03-07",
        "VisaCardNumber": "4419523453882878",
        "MastercardNumber": "2703940962948520",
        "AccountBalance": 3261.05
    },
    {
        "ID": "8109115515353",
        "Name": "Thomas Gay",
        "Lastname": "Ortiz",
        "PhoneNumber": "165042577",
        "Country": "Saint Barthelemy",
        "Text": "What evening dream across table report. Really agree happen money many.\nPlant study compare anything show woman. Second inside measure. Stage form believe boy recognize.",
        "Date": "2005-04-15",
        "VisaCardNumber": "4538582741473573",
        "MastercardNumber": "2511178360928651",
        "AccountBalance": 6811.04
    },
    {
        "ID": "1011122035942",
        "Name": "Joseph Williams",
        "Lastname": "Smith",
        "PhoneNumber": "374281719",
        "Country": "Mauritania",
        "Text": "Remember middle stand. Act but list sea various bill all early. Leg remember real record care resource.\nTax we road yeah baby leader why. Offer tough keep nice. Institution simply agree question.",
        "Date": "1989-10-31",
        "VisaCardNumber": "4964289802132717",
        "MastercardNumber": "5552857879943458",
        "AccountBalance": 1754.94
    },
    {
        "ID": "8004053590882",
        "Name": "Kimberly Ray",
        "Lastname": "Simpson",
        "PhoneNumber": "689260755",
        "Country": "Malaysia",
        "Text": "Actually politics morning board. Traditional course try do little service.\nWork myself across record next. Kid officer customer area significant.",
        "Date": "2019-05-16",
        "VisaCardNumber": "4228461513735375",
        "MastercardNumber": "2369299493906043",
        "AccountBalance": 5069.55
    },
    {
        "ID": "3010244142344",
        "Name": "Miguel Pierce",
        "Lastname": "Williams",
        "PhoneNumber": "705146236",
        "Country": "Cayman Islands",
        "Text": "Including how else sure economic authority growth. Quite establish that speak source. Deal garden last produce seat. Anything everybody city onto speech clear remember collection.",
        "Date": "1988-06-02",
        "VisaCardNumber": "4810412489306075",
        "MastercardNumber": "2249796326791886",
        "AccountBalance": 7024.28
    },
    {
        "ID": "1310293299358",
        "Name": "Jeffrey Jones",
        "Lastname": "Mcclain",
        "PhoneNumber": "374684595",
        "Country": "Antigua and Barbuda",
        "Text": "Share apply into gun himself off. Wish body front cultural participant begin. National true suffer see focus laugh.\nGrowth security dog. Current history season.",
        "Date": "1987-10-01",
        "VisaCardNumber": "4657650028634319",
        "MastercardNumber": "2222406243800452",
        "AccountBalance": 8039.3
    },
    {
        "ID": "0109091460795",
        "Name": "Kenneth Mason",
        "Lastname": "Sanchez",
        "PhoneNumber": "682289279",
        "Country": "Kenya",
        "Text": "Attention peace fact south. Toward nation for system those present enter.\nFloor compare ball front often realize. Teach talk religious space until why.",
        "Date": "1994-06-26",
        "VisaCardNumber": "4843234587283803",
        "MastercardNumber": "2720815052997224",
        "AccountBalance": 4492.06
    },
    {
        "ID": "8604219474834",
        "Name": "Nathan Sandoval",
        "Lastname": "Quinn",
        "PhoneNumber": "004465304",
        "Country": "Guernsey",
        "Text": "Sign production theory yet trial. Instead voice result support represent amount ten appear.",
        "Date": "2021-12-11",
        "VisaCardNumber": "4218153841187518",
        "MastercardNumber": "2254686434607698",
        "AccountBalance": 9271.52
    },
    {
        "ID": "7008230749850",
        "Name": "Kyle Barber",
        "Lastname": "Smith",
        "PhoneNumber": "208464840",
        "Country": "Monaco",
        "Text": "Sort everybody financial. Figure win fall region.\nEnvironment blue quickly stand small throw.",
        "Date": "1994-10-14",
        "VisaCardNumber": "4899602656518395",
        "MastercardNumber": "2285032339822293",
        "AccountBalance": 538.48
    },
    {
        "ID": "3311308790212",
        "Name": "Anthony Osborne",
        "Lastname": "Maldonado",
        "PhoneNumber": "921758069",
        "Country": "Colombia",
        "Text": "Make use clearly shoulder. Series much medical Mr. Project particular central without.\nPlace me rock guy term should. Only agreement tax southern firm worry. Customer himself green camera sound hair.",
        "Date": "1986-12-13",
        "VisaCardNumber": "4420772682847296",
        "MastercardNumber": "2269536975242004",
        "AccountBalance": 7200.88
    },
    {
        "ID": "1809278428938",
        "Name": "Julia Golden",
        "Lastname": "Burton",
        "PhoneNumber": "770372406",
        "Country": "Saint Kitts and Nevis",
        "Text": "Explain possible join. Somebody floor rich amount common federal article candidate. Her learn spring store.",
        "Date": "2014-02-25",
        "VisaCardNumber": "4875569583852544",
        "MastercardNumber": "5519809267907688",
        "AccountBalance": 1790.19
    },
    {
        "ID": "3511091992152",
        "Name": "Veronica Jones",
        "Lastname": "Carey",
        "PhoneNumber": "564041871",
        "Country": "Tunisia",
        "Text": "Forward thought class cause design. Behavior pass ability. Ability little a civil.",
        "Date": "1997-05-30",
        "VisaCardNumber": "4986499783411758",
        "MastercardNumber": "2232660777114502",
        "AccountBalance": 6105.49
    },
    {
        "ID": "7707174023548",
        "Name": "Jesse Day",
        "Lastname": "Koch",
        "PhoneNumber": "564394537",
        "Country": "Guinea",
        "Text": "Gas could artist century usually throw themselves. Year foreign personal science politics read.\nRole collection general avoid their admit. Character pull that tend camera south toward.",
        "Date": "1975-08-11",
        "VisaCardNumber": "4523466773154268",
        "MastercardNumber": "2720045292372505",
        "AccountBalance": 7939.5
    },
    {
        "ID": "6606275751969",
        "Name": "Casey Hernandez",
        "Lastname": "Cardenas",
        "PhoneNumber": "547489421",
        "Country": "Bulgaria",
        "Text": "Walk style wear song perform general. Red would see note power election. Across big natural history those keep you.",
        "Date": "1995-11-07",
        "VisaCardNumber": "4607847705806779",
        "MastercardNumber": "2491791041724143",
        "AccountBalance": 6456.86
    },
    {
        "ID": "1410114993051",
        "Name": "James Maxwell",
        "Lastname": "Crawford",
        "PhoneNumber": "749101803",
        "Country": "Slovakia (Slovak Republic)",
        "Text": "Same seem course decade lawyer area. Congress happy enter.\nThat common view rest example. What character say.",
        "Date": "1991-01-15",
        "VisaCardNumber": "4488274690819267",
        "MastercardNumber": "2268136763361495",
        "AccountBalance": 2333.93
    },
    {
        "ID": "0805108938964",
        "Name": "Ian Richard",
        "Lastname": "Hogan",
        "PhoneNumber": "979749302",
        "Country": "South Georgia and the South Sandwich Islands",
        "Text": "Institution baby talk hit challenge.\nCountry book charge capital article her dinner general. Wife himself certain benefit contain. Yard key prevent smile ability deep.",
        "Date": "1974-11-07",
        "VisaCardNumber": "4968019646630477",
        "MastercardNumber": "5256598680207456",
        "AccountBalance": 9421.57
    },
    {
        "ID": "6001020448781",
        "Name": "Steve Newton",
        "Lastname": "Hoover",
        "PhoneNumber": "561794765",
        "Country": "Uganda",
        "Text": "Summer seek can morning true. Assume left report situation. Spend listen find officer.\nTheir you show western skill. Not chance win himself respond state soon.",
        "Date": "2015-09-25",
        "VisaCardNumber": "4371817750633273",
        "MastercardNumber": "2720036966304254",
        "AccountBalance": 1117.01
    },
    {
        "ID": "3205045984142",
        "Name": "Timothy Mccann",
        "Lastname": "Meyer",
        "PhoneNumber": "005811437",
        "Country": "Vietnam",
        "Text": "Prove particularly artist middle staff range.\nChallenge something either fill early hour. Them effort door middle majority off education. Can laugh lose series recently.",
        "Date": "1988-01-18",
        "VisaCardNumber": "4340396243279455",
        "MastercardNumber": "2720878296919529",
        "AccountBalance": 8414.47
    },
    {
        "ID": "3103316955188",
        "Name": "Heidi Woods",
        "Lastname": "Larson",
        "PhoneNumber": "751698354",
        "Country": "Suriname",
        "Text": "Others on every. Dog not reflect agreement.",
        "Date": "1998-02-26",
        "VisaCardNumber": "4049100473358177",
        "MastercardNumber": "5548836594792074",
        "AccountBalance": 9028.27
    },
    {
        "ID": "0710319735186",
        "Name": "Brian Martinez MD",
        "Lastname": "Orozco",
        "PhoneNumber": "672205792",
        "Country": "Nepal",
        "Text": "Establish generation just. Whole onto high newspaper design.\nWear nothing floor recent head yourself occur. Save family goal. Major imagine state agree often.",
        "Date": "2007-05-09",
        "VisaCardNumber": "4636624573984029",
        "MastercardNumber": "5131217158340183",
        "AccountBalance": 2797.38
    },
    {
        "ID": "7008019372280",
        "Name": "Alexander Wilson",
        "Lastname": "Anderson",
        "PhoneNumber": "502213956",
        "Country": "Puerto Rico",
        "Text": "Foreign look success network maintain final product sit. Say exist family wait short contain industry contain.",
        "Date": "2017-01-09",
        "VisaCardNumber": "4822054028281785",
        "MastercardNumber": "2241710913779988",
        "AccountBalance": 4850.53
    },
    {
        "ID": "0203181680750",
        "Name": "Andrea Craig",
        "Lastname": "Bell",
        "PhoneNumber": "785727335",
        "Country": "Liechtenstein",
        "Text": "Writer next specific career each. Focus discussion subject everything evidence however.",
        "Date": "2012-01-24",
        "VisaCardNumber": "4448844180857925",
        "MastercardNumber": "2410079575791854",
        "AccountBalance": 8097.8
    },
    {
        "ID": "3904095494220",
        "Name": "Kyle Gonzalez",
        "Lastname": "Solis",
        "PhoneNumber": "520760995",
        "Country": "Ecuador",
        "Text": "Never indicate shoulder state. Probably special news night general popular significant.",
        "Date": "1975-08-09",
        "VisaCardNumber": "4187339338755910",
        "MastercardNumber": "5598201862919132",
        "AccountBalance": 5413.37
    },
    {
        "ID": "2903227309780",
        "Name": "Pamela Porter",
        "Lastname": "Hale",
        "PhoneNumber": "833868322",
        "Country": "Burundi",
        "Text": "Senior responsibility sea tell spend before. Past near article term over. Blue mouth person food necessary word.\nAhead either various participant political section shake. Yet actually few very.",
        "Date": "2000-04-13",
        "VisaCardNumber": "4236438880562046",
        "MastercardNumber": "2494853129876828",
        "AccountBalance": 82.36
    },
    {
        "ID": "3907072732353",
        "Name": "Julie Smith",
        "Lastname": "Ayers",
        "PhoneNumber": "832244110",
        "Country": "Chad",
        "Text": "Hour military take conference.\nAudience next exist financial act. West hear contain personal happen.\nOne admit early.\nOne on window recognize fine. Conference stage why. Almost will election.",
        "Date": "2005-12-10",
        "VisaCardNumber": "4393174419902226",
        "MastercardNumber": "2491935816370216",
        "AccountBalance": 7152.89
    },
    {
        "ID": "4509307331967",
        "Name": "Sarah Briggs",
        "Lastname": "Castillo",
        "PhoneNumber": "807650725",
        "Country": "Monaco",
        "Text": "Rate way ability. I summer weight stage either then. Far pass real of reach draw yard.\nTotal task exactly happy. Clearly generation bag. Science those item last rock compare.",
        "Date": "1988-05-13",
        "VisaCardNumber": "4051009430327016",
        "MastercardNumber": "5493567140689796",
        "AccountBalance": 4439.05
    },
    {
        "ID": "2208077842103",
        "Name": "Amanda Bryant",
        "Lastname": "Wilson",
        "PhoneNumber": "371724775",
        "Country": "Norway",
        "Text": "State bring draw mind. Peace find trial because sit personal value local.\nBecause sign present. Land lead glass go same cost. Remember east best bit us.",
        "Date": "2019-05-24",
        "VisaCardNumber": "4487485150690557",
        "MastercardNumber": "2707221511254157",
        "AccountBalance": 4098.38
    },
    {
        "ID": "6302187660126",
        "Name": "Melanie Stewart",
        "Lastname": "Peterson",
        "PhoneNumber": "967648930",
        "Country": "Vietnam",
        "Text": "Production billion down him back. Democrat question history college. Shoulder their example least rich image sometimes model.\nIdentify election require capital. Deal parent others catch few.",
        "Date": "1971-04-20",
        "VisaCardNumber": "4679975075720065",
        "MastercardNumber": "2223708484108829",
        "AccountBalance": 1665.49
    },
    {
        "ID": "0301276145036",
        "Name": "Tina Roberson",
        "Lastname": "Wade",
        "PhoneNumber": "509954787",
        "Country": "Pitcairn Islands",
        "Text": "Next sense quite position apply. Citizen actually minute matter team important can. Special southern vote cold lawyer as.",
        "Date": "2012-04-14",
        "VisaCardNumber": "4316920076430545",
        "MastercardNumber": "2262725278699021",
        "AccountBalance": 8313.01
    },
    {
        "ID": "8105012041941",
        "Name": "James Hall",
        "Lastname": "Jordan",
        "PhoneNumber": "948044421",
        "Country": "Comoros",
        "Text": "No population instead lose side nor know. Often citizen couple whose natural building. Tell suddenly full before.\nThose project Mr operation fly.",
        "Date": "1997-09-07",
        "VisaCardNumber": "4632477113848350",
        "MastercardNumber": "2247171025989904",
        "AccountBalance": 7521.1
    },
    {
        "ID": "5702028038981",
        "Name": "Mr. Jeffrey Anderson",
        "Lastname": "Wise",
        "PhoneNumber": "888773254",
        "Country": "Egypt",
        "Text": "Really push pay from citizen television. Experience story idea our whatever probably church. Language evidence law chance budget however.\nParticularly professor spring mind there.",
        "Date": "1999-10-07",
        "VisaCardNumber": "4651113793742169",
        "MastercardNumber": "2269172654009751",
        "AccountBalance": 703.99
    },
    {
        "ID": "4908157666083",
        "Name": "Maria Taylor",
        "Lastname": "Haas",
        "PhoneNumber": "934569050",
        "Country": "Guyana",
        "Text": "Director medical building present tax give attack out. Office the product.\nCoach above item effort step. Son character culture table.\nRead me paper out officer help its for.",
        "Date": "2015-07-13",
        "VisaCardNumber": "4561260735122452",
        "MastercardNumber": "2273587004894517",
        "AccountBalance": 6548.19
    },
    {
        "ID": "0411063034920",
        "Name": "Kathy Jackson",
        "Lastname": "Jones",
        "PhoneNumber": "316252217",
        "Country": "Kenya",
        "Text": "Yet walk production change main young family three. Drop financial thought statement prove. Dinner test build step.\nEdge do offer two arrive. Music difficult base because.",
        "Date": "2019-10-03",
        "VisaCardNumber": "4728055821100564",
        "MastercardNumber": "5374915334600596",
        "AccountBalance": 1360.6
    },
    {
        "ID": "2011035399478",
        "Name": "Anthony Allison",
        "Lastname": "Conner",
        "PhoneNumber": "230372198",
        "Country": "Western Sahara",
        "Text": "One television population whole peace. Side chair where happy choose type.\nCut large political least way soon provide. Cost him policy understand.",
        "Date": "2016-01-04",
        "VisaCardNumber": "4164174640372865",
        "MastercardNumber": "5254307940814453",
        "AccountBalance": 4385.15
    },
    {
        "ID": "7701255243457",
        "Name": "Lori Rogers",
        "Lastname": "Mcintyre",
        "PhoneNumber": "996308588",
        "Country": "Bermuda",
        "Text": "Decision court some organization. Us fill close human doctor goal.\nDescribe surface even detail participant authority. Cost social game month deal smile science. Eat fine else think prevent.",
        "Date": "2014-05-04",
        "VisaCardNumber": "4316882953949734",
        "MastercardNumber": "2707232464273821",
        "AccountBalance": 591.38
    },
    {
        "ID": "1301250741759",
        "Name": "Kayla Wilson",
        "Lastname": "Howard",
        "PhoneNumber": "952063503",
        "Country": "Puerto Rico",
        "Text": "Investment stuff nearly party. Human thus already friend picture.\nReady almost what stay. Prove often physical walk one eight matter.",
        "Date": "1992-06-06",
        "VisaCardNumber": "4737626811965866",
        "MastercardNumber": "2279492253939457",
        "AccountBalance": 7191.89
    },
    {
        "ID": "8507116706413",
        "Name": "Martha Cook",
        "Lastname": "Davis",
        "PhoneNumber": "669354958",
        "Country": "Singapore",
        "Text": "Offer they artist often himself. Week pretty why people evidence finally. Commercial never box them.\nWar serve question. One center need participant.\nAdministration give answer. Safe lot player.",
        "Date": "2004-03-31",
        "VisaCardNumber": "4686805816532290",
        "MastercardNumber": "2272494471189433",
        "AccountBalance": 458.75
    },
    {
        "ID": "8010107900608",
        "Name": "Cory Thompson",
        "Lastname": "Martinez",
        "PhoneNumber": "748680311",
        "Country": "Angola",
        "Text": "Art that check would successful door. Kid artist threat across where. Usually factor white trip will.\nLaw notice ago dog what visit offer. Remain organization through whatever second.",
        "Date": "2010-09-17",
        "VisaCardNumber": "4651321707579474",
        "MastercardNumber": "2286210407830898",
        "AccountBalance": 2828.8
    },
    {
        "ID": "7312054629541",
        "Name": "Jessica Hughes",
        "Lastname": "Curry",
        "PhoneNumber": "698018157",
        "Country": "Djibouti",
        "Text": "Baby then ten give rich great surface same. During key later. One class economy southern assume.\nGoal toward along statement painting region responsibility. Central effect something stay.",
        "Date": "2004-02-17",
        "VisaCardNumber": "4496956499952550",
        "MastercardNumber": "2235551091030929",
        "AccountBalance": 8125.96
    },
    {
        "ID": "1302189367584",
        "Name": "Taylor Haney",
        "Lastname": "Khan",
        "PhoneNumber": "460276378",
        "Country": "Czech Republic",
        "Text": "Quality four personal. Finally lay school in follow usually material. Stuff investment similar movement concern.\nHold station thousand us make force. Ball effort sport home wrong military include.",
        "Date": "2009-09-04",
        "VisaCardNumber": "4992391636066776",
        "MastercardNumber": "5153036610454256",
        "AccountBalance": 7415.75
    },
    {
        "ID": "1908108988421",
        "Name": "Kelly Henderson",
        "Lastname": "Cabrera",
        "PhoneNumber": "307696845",
        "Country": "Ukraine",
        "Text": "Standard fly base seek fund. Situation Congress employee gas build strategy own. Budget couple amount anyone.\nSecond group amount often defense run west. Quite crime memory term wall.",
        "Date": "2012-08-06",
        "VisaCardNumber": "4928167285954507",
        "MastercardNumber": "2231541168408417",
        "AccountBalance": 3896.64
    },
    {
        "ID": "0511177619374",
        "Name": "Daniel Campbell",
        "Lastname": "Mccarthy",
        "PhoneNumber": "664306779",
        "Country": "New Zealand",
        "Text": "Method knowledge eat central onto start. Record south wish. Specific organization add author maybe indeed.\nLoss poor whose laugh woman. One wonder leave adult something visit treatment check.",
        "Date": "2006-01-31",
        "VisaCardNumber": "4731718458333809",
        "MastercardNumber": "2221131222315378",
        "AccountBalance": 2653.29
    },
    {
        "ID": "9202123396847",
        "Name": "Janet Stafford",
        "Lastname": "Schwartz",
        "PhoneNumber": "200991715",
        "Country": "Burundi",
        "Text": "Happy over rise maintain unit. Information long almost way give boy box.\nParticularly as outside reduce little stuff successful. Somebody former short argue beat mention.",
        "Date": "2002-06-30",
        "VisaCardNumber": "4663901452745143",
        "MastercardNumber": "2228059505971174",
        "AccountBalance": 4651.98
    },
    {
        "ID": "5309014392743",
        "Name": "William Marshall",
        "Lastname": "Rogers",
        "PhoneNumber": "068467434",
        "Country": "Niger",
        "Text": "Easy five cut everything ahead detail hard break. Only nor common difficult. Weight line both which.\nTalk science around stay statement. Address light real a wish drive push.",
        "Date": "1978-11-08",
        "VisaCardNumber": "4616380603742341",
        "MastercardNumber": "2521003708199930",
        "AccountBalance": 1679.1
    },
    {
        "ID": "5809046080489",
        "Name": "Stephanie Escobar",
        "Lastname": "Martinez",
        "PhoneNumber": "581575820",
        "Country": "Azerbaijan",
        "Text": "Source security home window prevent mouth. Senior become every high so natural. Blue section control opportunity. Begin husband say center subject enter example.",
        "Date": "1976-06-09",
        "VisaCardNumber": "4420466180270842",
        "MastercardNumber": "5119152660753597",
        "AccountBalance": 9975.35
    },
    {
        "ID": "3010160071420",
        "Name": "Antonio Andersen",
        "Lastname": "Shaffer",
        "PhoneNumber": "148800923",
        "Country": "Nicaragua",
        "Text": "West truth central only. Congress hot do store. Approach real business officer stock fire.",
        "Date": "1990-10-30",
        "VisaCardNumber": "4303367977911642",
        "MastercardNumber": "2229341052244273",
        "AccountBalance": 5239.48
    },
    {
        "ID": "1604140773685",
        "Name": "Michael Johnson",
        "Lastname": "Smith",
        "PhoneNumber": "486431166",
        "Country": "French Guiana",
        "Text": "Perform so about law nearly case happy. Want enter better use.\nBudget public health time. Science rule entire agency market north. Law and hundred mean position decade.",
        "Date": "1995-05-14",
        "VisaCardNumber": "4771976301569026",
        "MastercardNumber": "2703709071861159",
        "AccountBalance": 4561.07
    },
    {
        "ID": "6704260378862",
        "Name": "Linda Rivera",
        "Lastname": "Chapman",
        "PhoneNumber": "744696188",
        "Country": "Indonesia",
        "Text": "Number against small language piece easy sense. Heart face behavior song easy. Table local site.",
        "Date": "1991-05-27",
        "VisaCardNumber": "4621715297160032",
        "MastercardNumber": "2299015937386187",
        "AccountBalance": 6146.95
    },
    {
        "ID": "0803058546211",
        "Name": "Corey Coleman",
        "Lastname": "Knight",
        "PhoneNumber": "786073598",
        "Country": "Costa Rica",
        "Text": "Brother important these late. Race before with cost industry.\nList feeling face hundred center significant different. Sure series staff beat carry or. Chair begin floor good.",
        "Date": "2017-02-01",
        "VisaCardNumber": "4460210742079403",
        "MastercardNumber": "5490882421355303",
        "AccountBalance": 7481.27
    },
    {
        "ID": "2404090728618",
        "Name": "Kari Winters",
        "Lastname": "Carter",
        "PhoneNumber": "838174009",
        "Country": "Macao",
        "Text": "Action room dark management minute. Imagine worker put modern could color.\nInternational pull decision identify contain large almost. Adult across upon activity. Brother chair body picture.",
        "Date": "1979-05-17",
        "VisaCardNumber": "4497696695269602",
        "MastercardNumber": "2286432808102384",
        "AccountBalance": 1407.9
    },
    {
        "ID": "1003298064385",
        "Name": "Richard Schroeder",
        "Lastname": "Edwards",
        "PhoneNumber": "440615848",
        "Country": "Bhutan",
        "Text": "Defense police anyone enter sure. Military because enough society.\nToward follow oil operation. Company response social full near black.",
        "Date": "1996-10-27",
        "VisaCardNumber": "4733502572859107",
        "MastercardNumber": "2231627003598239",
        "AccountBalance": 4360.16
    },
    {
        "ID": "6012216041123",
        "Name": "Alex Drake",
        "Lastname": "Cox",
        "PhoneNumber": "342514535",
        "Country": "Saint Lucia",
        "Text": "Before consider rather. Center across easy kind consumer year cold plan.",
        "Date": "2017-09-11",
        "VisaCardNumber": "4548277948153460",
        "MastercardNumber": "5314095777180324",
        "AccountBalance": 2827.75
    },
    {
        "ID": "9506100474042",
        "Name": "Emily Padilla",
        "Lastname": "Jackson",
        "PhoneNumber": "277103004",
        "Country": "South Africa",
        "Text": "Brother her camera. Which writer yeah whatever. Why reach director make your.\nBecause outside to into activity far standard sea. Various artist employee. Check prevent late.",
        "Date": "2000-01-11",
        "VisaCardNumber": "4735823903296217",
        "MastercardNumber": "2479414657153970",
        "AccountBalance": 5217.13
    },
    {
        "ID": "0712293111756",
        "Name": "Kaitlyn Martinez",
        "Lastname": "Cervantes",
        "PhoneNumber": "136767586",
        "Country": "Switzerland",
        "Text": "Agreement fund such affect sort school prove successful. Information though remain size. Evidence everyone ask table or.",
        "Date": "2017-04-25",
        "VisaCardNumber": "4873664887679834",
        "MastercardNumber": "5394143381417030",
        "AccountBalance": 4115.51
    },
    {
        "ID": "5708081871902",
        "Name": "Brian Underwood",
        "Lastname": "Alvarado",
        "PhoneNumber": "711399110",
        "Country": "Hong Kong",
        "Text": "Now might impact network time million. Certainly pick close husband approach.\nBehavior control Congress trip difficult. Very drive product they list card guy.",
        "Date": "1982-07-29",
        "VisaCardNumber": "4841963996274241",
        "MastercardNumber": "2245976787178047",
        "AccountBalance": 1308.7
    },
    {
        "ID": "5012211784767",
        "Name": "Sergio Villegas",
        "Lastname": "Martin",
        "PhoneNumber": "296838618",
        "Country": "Angola",
        "Text": "Board set they son include two tell.\nTax grow writer almost might believe. Fund put respond.\nMovie environment population meet weight the operation. Company knowledge represent instead tax.",
        "Date": "2003-02-20",
        "VisaCardNumber": "4604077386225288",
        "MastercardNumber": "5375051331930528",
        "AccountBalance": 7666.73
    },
    {
        "ID": "2110291193598",
        "Name": "Patricia Long",
        "Lastname": "Goodman",
        "PhoneNumber": "821023444",
        "Country": "Saint Barthelemy",
        "Text": "Dog interest traditional grow artist rock. Discuss effort move cold prove dinner everybody program. Others plant reflect authority hear feel raise majority. Magazine same side serve step manager.",
        "Date": "2015-09-17",
        "VisaCardNumber": "4844635358500721",
        "MastercardNumber": "2329788722394806",
        "AccountBalance": 6249.06
    },
    {
        "ID": "2209179308316",
        "Name": "Oscar Fleming",
        "Lastname": "Brown",
        "PhoneNumber": "158359516",
        "Country": "Marshall Islands",
        "Text": "Beyond make matter last next subject card. Why imagine dinner political traditional significant about. Effect someone well music.",
        "Date": "1973-04-05",
        "VisaCardNumber": "4277780753054977",
        "MastercardNumber": "5393928881186742",
        "AccountBalance": 6070.06
    },
    {
        "ID": "8810254983257",
        "Name": "Crystal Gomez",
        "Lastname": "Wright",
        "PhoneNumber": "650571529",
        "Country": "Tajikistan",
        "Text": "Sense audience arrive even half financial number. Trip book know.",
        "Date": "1980-07-17",
        "VisaCardNumber": "4508328250769845",
        "MastercardNumber": "2720301703749934",
        "AccountBalance": 8009.22
    },
    {
        "ID": "0604048104235",
        "Name": "Thomas Smith",
        "Lastname": "Smith",
        "PhoneNumber": "731649511",
        "Country": "Heard Island and McDonald Islands",
        "Text": "Anything fall how opportunity still picture. Look which up ten gas appear second. Next hope carry last.\nBegin writer hospital bit decide. Right value religious. Build TV population rest head open.",
        "Date": "1993-09-29",
        "VisaCardNumber": "4302912715679893",
        "MastercardNumber": "2710600780872630",
        "AccountBalance": 2595.18
    },
    {
        "ID": "5003203305210",
        "Name": "Peter Clark",
        "Lastname": "White",
        "PhoneNumber": "164841938",
        "Country": "Zimbabwe",
        "Text": "Very nearly easy call TV. Line break situation husband. Describe kitchen red wait later. Support note travel find foot just read.",
        "Date": "1995-03-14",
        "VisaCardNumber": "4111920408064282",
        "MastercardNumber": "2238255944031418",
        "AccountBalance": 5518.52
    },
    {
        "ID": "9507071309338",
        "Name": "Melinda Kennedy",
        "Lastname": "Juarez",
        "PhoneNumber": "372928594",
        "Country": "Croatia",
        "Text": "Similar view civil whether doctor. Skill team collection participant degree.\nLess color next tough short. Less enjoy decide collection executive cause.\nBody heart together four before toward.",
        "Date": "1999-05-17",
        "VisaCardNumber": "4188328130858682",
        "MastercardNumber": "2340744961804158",
        "AccountBalance": 1479.53
    },
    {
        "ID": "1209197758484",
        "Name": "Richard Wheeler",
        "Lastname": "Salazar",
        "PhoneNumber": "597416098",
        "Country": "Guinea-Bissau",
        "Text": "Also agent especially reflect. Someone line PM respond why.\nPainting two must evening voice view man. Between despite until turn occur.",
        "Date": "1999-06-17",
        "VisaCardNumber": "4838213919354778",
        "MastercardNumber": "2709038992490680",
        "AccountBalance": 4914.29
    },
    {
        "ID": "2110211184611",
        "Name": "Elizabeth Jensen DDS",
        "Lastname": "Lloyd",
        "PhoneNumber": "230164401",
        "Country": "Senegal",
        "Text": "Picture attack against smile. Sport some give edge government score. Put remember present certain pressure listen professional.",
        "Date": "2022-10-29",
        "VisaCardNumber": "4439394757067707",
        "MastercardNumber": "5399744250091692",
        "AccountBalance": 2429.41
    },
    {
        "ID": "0102216712160",
        "Name": "Martin Crawford",
        "Lastname": "Brown",
        "PhoneNumber": "054302831",
        "Country": "Tokelau",
        "Text": "Business drop central. Organization staff particular poor president.\nLetter stuff listen participant know. Kind police attack certainly figure speech.",
        "Date": "2006-01-10",
        "VisaCardNumber": "4908452092114329",
        "MastercardNumber": "5244641079676017",
        "AccountBalance": 134.5
    },
    {
        "ID": "7509143623429",
        "Name": "Daniel Wade",
        "Lastname": "Kelley",
        "PhoneNumber": "375695327",
        "Country": "Congo",
        "Text": "Especially line notice anything toward by dream. Customer party what those.\nFear do debate fight.\nA pick remain ability figure car. Pattern lose these matter fight source light.",
        "Date": "2007-05-23",
        "VisaCardNumber": "4036829517855906",
        "MastercardNumber": "2230693839293685",
        "AccountBalance": 4911.26
    },
    {
        "ID": "1811155687431",
        "Name": "Sarah Harmon",
        "Lastname": "Caldwell",
        "PhoneNumber": "320184027",
        "Country": "Trinidad and Tobago",
        "Text": "Pressure major physical join already dinner. Anything staff quite speech east sense. Interest tree also east now environmental system. Loss serious attorney morning career perhaps.",
        "Date": "2013-11-23",
        "VisaCardNumber": "4542254345835193",
        "MastercardNumber": "2240918296210148",
        "AccountBalance": 2532.09
    },
    {
        "ID": "1611073947340",
        "Name": "Mark Butler",
        "Lastname": "Knapp",
        "PhoneNumber": "957776787",
        "Country": "American Samoa",
        "Text": "Individual key visit Mrs campaign really marriage. Present film college game test ability second.\nTell prevent necessary particular scene reflect. Know evening seem member.",
        "Date": "2013-06-22",
        "VisaCardNumber": "4480221787780033",
        "MastercardNumber": "2241298823802009",
        "AccountBalance": 3165.61
    },
    {
        "ID": "7907105614575",
        "Name": "Keith Price",
        "Lastname": "Smith",
        "PhoneNumber": "832366574",
        "Country": "Azerbaijan",
        "Text": "Green traditional international artist newspaper local public. Attack base education evening once. Policy prepare political couple term.",
        "Date": "1999-11-05",
        "VisaCardNumber": "4123454497188238",
        "MastercardNumber": "5112166958527874",
        "AccountBalance": 6576.23
    },
    {
        "ID": "6111105689173",
        "Name": "Lisa Monroe",
        "Lastname": "Mcdonald",
        "PhoneNumber": "753963403",
        "Country": "Paraguay",
        "Text": "Sit recognize something adult its. Heart nice government tonight with such.\nRadio local tax marriage. Mean election join listen fast himself.",
        "Date": "2006-05-28",
        "VisaCardNumber": "4738736239971880",
        "MastercardNumber": "5194868486380145",
        "AccountBalance": 9459.28
    }
]